metadata_etl/__init__.py
metadata_etl/clone_hdf5.py
metadata_etl/extract/DataLoader.py
metadata_etl/extract/InputProcessor.py
metadata_etl/extract/InputValidator.py
metadata_etl/load/MetadataInterface.py
metadata_etl/load/ServiceInterface.py
metadata_etl/mdc_api.py
metadata_etl/metadata_etl.py
metadata_etl/transform/MetadataExtractor.py
metadata_etl/utils/CommandLine.py
metadata_etl/utils/DataLoader.py
metadata_etl/utils/DataView.py
metadata_etl/utils/Trace.py
metadata_etl/utils/__init__.py
metadata_etl/utils/defines.py
metadata_etl/utils/utils.py
tests/__init__.py
tests/mdc_api_responses_mock.py
tests/secrets.py
tests/test_DataLoader/data/RAW-R0190-DA03-S00000.h5
tests/test_DataLoader/dataset.data
tests/test_DataLoader/parameters.json
tests/test_DataLoader/specs.txt
tests/test_DataLoader.py
tests/test_DataView.py
tests/test_Parameter.py
tests/test_Trace.py
tests/test_parameters_crud.py
tests/test_utils.py
metadata_etl-0.2.2.dist-info/AUTHORS.rst
metadata_etl-0.2.2.dist-info/METADATA
metadata_etl-0.2.2.dist-info/WHEEL
metadata_etl-0.2.2.dist-info/entry_points.txt
metadata_etl-0.2.2.dist-info/RECORD
