Metadata-Version: 2.3
Name: metadata_etl
Version: 0.2.2
Summary: Implement the metadata ETL process to extract metadata from offline research data (HDF5 files) and inject it to the metadata catalog 
License: XFEL
Keywords: ETL,metadata,research data,hdf5,REST
Author: Djelloul Boukhelef
Author-email: djelloul.boukhelef@xfel.eu
Requires-Python: >=3.10,<4.0
Classifier: License :: Other/Proprietary License
Classifier: Programming Language :: Python :: 3
Classifier: Programming Language :: Python :: 3.10
Classifier: Programming Language :: Python :: 3.11
Classifier: Programming Language :: Python :: 3.12
Classifier: Programming Language :: Python :: 3.13
Requires-Dist: anywidget (>=0.9.13,<0.10.0)
Requires-Dist: argparse (>=1.4.0,<2.0.0)
Requires-Dist: coverage (>=7.4.1,<8.0.0)
Requires-Dist: datadir (>=1.1.0,<2.0.0)
Requires-Dist: h5py (>=3.10.0,<4.0.0)
Requires-Dist: ipyfilechooser (>=0.6.0,<0.7.0)
Requires-Dist: ipympl (>=0.9.6,<0.10.0)
Requires-Dist: ipython (>=8.31.0,<9.0.0)
Requires-Dist: ipywidgets (>=8.1.5,<9.0.0)
Requires-Dist: itables[widget] (>=2.2.4,<3.0.0)
Requires-Dist: jupyterlab-h5web (>=12.3.0,<13.0.0)
Requires-Dist: loguru (>=0.7.2,<0.8.0)
Requires-Dist: metadata-api (>=4.1.0,<5.0.0)
Requires-Dist: numpy (>=1.26.4,<2.0.0)
Requires-Dist: numpyencoder (>=0.3.0,<0.4.0)
Requires-Dist: oauthlib (>=3.2.2,<4.0.0)
Requires-Dist: pathlib (>=1.0.1,<2.0.0)
Requires-Dist: pycodestyle (>=2.11.1,<3.0.0)
Requires-Dist: pytest-datadir (>=1.5.0,<2.0.0)
Requires-Dist: requests-oauthlib (>=2.0.0,<3.0.0)
Project-URL: Homepage, https://git.xfel.eu/ITDM/metadata_etl/documentation
Project-URL: Repository, https://git.xfel.eu/ITDM/metadata_etl
